minedojo/__init__.py
minedojo/data/__init__.py
minedojo/data/download.py
minedojo/data/reddit_dataset.py
minedojo/data/wiki_dataset.py
minedojo/data/youtube_dataset.py
minedojo/sim/__init__.py
minedojo/sim/cmd_executor.py
minedojo/sim/config_sim_spec.py
minedojo/sim/handler.py
minedojo/sim/inventory.py
minedojo/sim/sim.py
minedojo/sim/spaces.py
minedojo/sim/Malmo/.gitattributes
minedojo/sim/Malmo/.gitignore
minedojo/sim/Malmo/.gitrepo
minedojo/sim/Malmo/LICENSE.txt
minedojo/sim/Malmo/README.md
minedojo/sim/Malmo/VERSION
minedojo/sim/Malmo/changelog.txt
minedojo/sim/Malmo/malmo.properties
minedojo/sim/Malmo/Minecraft/CMakeLists.txt
minedojo/sim/Malmo/Minecraft/CREDITS-fml.txt
minedojo/sim/Malmo/Minecraft/LICENSE-new.txt
minedojo/sim/Malmo/Minecraft/MinecraftForge-Credits.txt
minedojo/sim/Malmo/Minecraft/Paulscode IBXM Library License.txt
minedojo/sim/Malmo/Minecraft/Paulscode SoundSystem CodecIBXM License.txt
minedojo/sim/Malmo/Minecraft/README.txt
minedojo/sim/Malmo/Minecraft/build.gradle
minedojo/sim/Malmo/Minecraft/gradlew
minedojo/sim/Malmo/Minecraft/gradlew.bat
minedojo/sim/Malmo/Minecraft/launchClient.bat
minedojo/sim/Malmo/Minecraft/launchClient.sh
minedojo/sim/Malmo/Minecraft/launch_minecraft_in_background.py
minedojo/sim/Malmo/Minecraft/wait_for_port.sh
minedojo/sim/Malmo/Minecraft/gradle/wrapper/gradle-wrapper.jar
minedojo/sim/Malmo/Minecraft/gradle/wrapper/gradle-wrapper.properties
minedojo/sim/Malmo/Minecraft/run/options.txt
minedojo/sim/Malmo/Minecraft/run/config/forge.cfg
minedojo/sim/Malmo/Minecraft/run/config/forgeChunkLoading.cfg
minedojo/sim/Malmo/Minecraft/run/config/malmomodCLIENTPermanent.cfg
minedojo/sim/Malmo/Minecraft/shared_configs/Attach on 1044.run.xml
minedojo/sim/Malmo/Minecraft/shared_configs/Interactive + Auto-debugger.run.xml
minedojo/sim/Malmo/Minecraft/shared_configs/Wait For Port.run.xml
minedojo/sim/Malmo/Minecraft/shared_configs/interactive.py.run.xml
minedojo-0.1.dist-info/LICENSE
minedojo-0.1.dist-info/METADATA
minedojo-0.1.dist-info/WHEEL
minedojo-0.1.dist-info/top_level.txt
minedojo-0.1.dist-info/RECORD
