Metadata-Version: 2.1
Name: minedojo
Version: 0.1
Summary: research project
Home-page: http://github.com/MineDojo/MineDojo
Author: MineDojo Team
License: MIT License
Keywords: Deep Learning,Machine Learning
Platform: UNKNOWN
Classifier: Development Status :: 5 - Production/Stable
Classifier: Topic :: Scientific/Engineering :: Artificial Intelligence
Classifier: Environment :: Console
Classifier: Programming Language :: Python :: 3.9
Requires-Python: >=3.9
License-File: LICENSE
Requires-Dist: pyyaml
Requires-Dist: jinja2
Requires-Dist: gym (==0.21.0)
Requires-Dist: lxml
Requires-Dist: numpy
Requires-Dist: coloredlogs
Requires-Dist: xmltodict
Requires-Dist: Pyro4
Requires-Dist: psutil
Requires-Dist: opencv-python
Requires-Dist: multiprocess
Requires-Dist: pytest
Requires-Dist: daemoniker
Requires-Dist: tqdm
Requires-Dist: requests
Requires-Dist: mypy-extensions
Requires-Dist: jsonlines
Requires-Dist: praw
Requires-Dist: wget
Requires-Dist: importlib-resources
Requires-Dist: hydra-core
Requires-Dist: Pillow
